LICENSE
README.md
pyproject.toml
pyloggroup/__init__.py
pyloggroup/pyloggroup.py
pyloggroup-0.1.0.dist-info/METADATA
pyloggroup-0.1.0.dist-info/WHEEL
pyloggroup-0.1.0.dist-info/licenses/LICENSE
pyloggroup-0.1.0.dist-info/RECORD
