Metadata-Version: 2.3
Name: pyloggroup
Version: 0.1.0
Summary: A Python package for grouping logs and displaying them in a tree format for improved readability.
Project-URL: Homepage, https://github.com/GirishCodeAlchemy/pyloggroup
Project-URL: Issues, https://github.com/GirishCodeAlchemy/pyloggroup/issues
Author-email: GirishCodeAlchemy <girishcodealchemy@gmail.com>
License: MIT
License-File: LICENSE
Classifier: Intended Audience :: Developers
Classifier: License :: OSI Approved :: MIT License
Classifier: Operating System :: OS Independent
Classifier: Programming Language :: Python :: 3
Classifier: Topic :: Software Development :: Build Tools
Requires-Python: >=3.6
Provides-Extra: docs
